{"Sb5j+X+Oca8I5Ahu9EhfNg==":"lawyer-larry-gadon-sereno-620x413.jpg","mtTah/0AwXNwX7QTUOsMYQ==":"larry-gadon-sereno-impeachment-house_2018-04-13_08-53-9-800x534.jpg","XYQZe73f4aHDvSzlPrJ3fg==":"37077841_10204727729070560_1821642599719501824_n-240x243.jpg","UfROgYUHFdcgIhirKklKZg==":"ken-240x216.jpg","cGyp6bCeqeHfmzZWEglanA==":"matut-240x240.jpg","QG3Mbi4ZqisyUy8dXSOPOg==":"shanghai-night-traffic-hd-wallpaper-1920x1200.jpg","fpQlQOKm6WM8YRI3c6SGoQ==":"sign-traffic-typography-1920x1200.jpg","lMiFwx7YYjhkZffQ9CKGNw==":"pedestrian-jaywalking-night-street_htks3hp0_thumbnail-full01-1920x1080.jpg","+dP7GCiN/3LWm+9DlC3RVw==":"1577719-2000x1250.jpg","erFXaguxZchb2Zr4N+YgMQ==":"1184485-2000x1125.jpg","jqw2e6/WVWMlCSS1FMtPxQ==":"68739043-traffic-wallpapers-1680x1050.jpg","vNxfuBu36hhnkncA42fTNQ==":"79779577f314302bbd285e2f858754ea0f04-1680x1050.jpg","SeJwimXzwilGwDGxTXf5Yw==":"6069299-lamborghini-hd-wallpaper-1680x1050.jpg","jN2pl04gEPbC4tDQqKIFzQ==":"logo-192x144.png","tZjK07xj7e1tvCOYGfPd3Q==":"logo-254x191.png","dgIuE64doKJ4vQ0sav+jbA==":"logo-96x72.png","cnMyxnSUptmpHAbvL1Osbw==":"logo%20final-128x96.jpg","gydY19Sfhe/X17HJyn+McQ==":"logo%20final-128x96.png","sgZBMU9v9unOMaUHanH1TQ==":"logo%20final-254x191.png","ZorJkHguel8mDJBT9mfgFg==":"3-2000x1305.jpg","Y3lxsItULHQICpfhZRQN9Q==":"2-2000x1305.jpg","sTBNdq9J4bCCDTanqyO10Q==":"6-2000x1305.jpg","TzpVeAKnD/Anoq7B6RL70Q==":"6-1-2000x1305.jpg","KNY1tSMVsAL8F45SUcWskw==":"3-1-2000x1305.jpg","ihlkf69UyfSmhSyJ1Jvc6w==":"jumbotron.jpg"}